asincronico.vhd
library IEEE;
use IEEE.std_logic_1164.all;
use IEEE.numeric_std.all;

library work;
use work.estados_asincronico.all;

entity asinc is
    port (s1: in std_logic;
          s2: in std_logic;  
          qo: out std_logic
          );
end asinc;

architecture asinc_beh of asinc is
    signal current_state: asinc_states := E1;
begin
    P_ASINC: process(s1, s2)
    begin
        if (s1 = '0' and s2 = '0') then
            qo <= '0';
            current_state <= E1;
        elsif (s1 = '1' and s2 = '0') then
            if current_state = E1 then
                qo <= '1';
            else
                qo <= '0';
            end if;  
            current_state <= E2;  
        elsif (s1 = '0' and s2 = '1') then
            qo <= '0';
            current_state <= E3;
        elsif (s1 = '1' and s2 = '1') then
            qo <= '0';
            current_state <= E4; 
        end if;
    end process P_ASINC;
end asinc_beh;

contador.vhd
library IEEE;
use IEEE.std_logic_1164.all;
use IEEE.numeric_std.all;

entity counter is
    generic(N: natural := 4);

    port (ena: in std_logic;
          clk: in std_logic;  
          rst: in std_logic;
          count: out std_logic_vector(N-1 downto 0)
          );
end counter;

architecture counter_beh of counter is
    signal aux: unsigned(N-1 downto 0);
    signal max: integer := 15;
begin
    process(clk, rst)
    begin
        if rst = '1' then
            aux <= (others => '0');
        end if;
        if rising_edge(clk) then
            --Si está habilitado
            if ena = '1' and to_integer(unsigned(aux)) /= max then
                --Sumar
                aux <= aux + 1;
            end if;
            count <= std_logic_vector(aux); 
        end if;
    end process;
end counter_beh;

detector.vhd
library IEEE;
use IEEE.std_logic_1164.all;
use IEEE.numeric_std.all;

library work;
use work.estados_asincronico.all;

entity detector is
    generic(BITS_CONTADOR: natural := 4; 
            DELAY_CICLOS: natural := 4);
    port (s1: in std_logic;
          s2: in std_logic;
          clk_cont: in std_logic;
          alarma: out std_logic
          );
end detector;

architecture detector_beh of detector is
    --Entradas y salidas del contador (sincrónico)
    signal count: std_logic_vector(BITS_CONTADOR-1 downto 0);
    signal rst_cont: std_logic;
    signal delay_rst: std_logic;
    --Salida del comparador (entrada es "count")
    signal comp_out: std_logic;
    --Salida del asincrónico
    signal asinc_out: std_logic;
    --Entrada al bloque del delay
    signal delay_in: std_logic;
    --Señal auxiliar para manejar tiempo de matenido 
    --(cuatro ciclos de clks)
    signal delay_reg: std_logic_vector(DELAY_CICLOS-1 downto 0) := (others => '0');
    constant cero: std_logic_vector(DELAY_CICLOS-1 downto 0) := (others => '0'); 
begin
    --Sincrónico (contador 4 bits)
    COUNTER_INST : entity work.counter(counter_beh)
        generic map(N => BITS_CONTADOR)
        port map(
            ena => asinc_out,
            clk => clk_cont,
            rst => rst_cont,
            count => count
        );
    --Asincrónico
    ASINC_INST :  entity work.asinc(asinc_beh)
        port map(
            s1 => s1,
            s2 => s2,  
            qo => asinc_out
        );

    P_DETECTOR: process(clk_cont, s1, s2)
        begin
            --COMPARADOR
            --Salida del comparador es el bit más significativo
            -- del contador
            if rst_cont = '0' then
                comp_out <= count(BITS_CONTADOR-1);
            else
                comp_out <= '1';
            end if;
            if (comp_out = '0' and s1 = '1' and s2 = '1') then
                delay_in <= '1';
            else
                delay_in <= '0';
            end if;
            
            
            if rising_edge(clk_cont) then
                --RESET CONTADOR
                --Tiene delay de un ciclo
                if delay_rst = '1' then
                    rst_cont <= not asinc_out;
                    delay_rst <= '0';
                end if;
                delay_rst <= '1';

                --DELAY ALARMA
                --Manejo del delay en la alarma (se mantiene 
                --durante DELAY_CICLOS)
                delay_reg(DELAY_CICLOS-1 downto 1) 
                <= delay_reg(DELAY_CICLOS-2 downto 0);
                delay_reg(0) <= delay_in;
            end if;

    end process P_DETECTOR;

    --Salida del delay
    alarma <= '1' when delay_reg /= cero else '0';
    
end detector_beh;

detector_tb.vhd
library IEEE;
use IEEE.std_logic_1164.all;
use IEEE.numeric_std.all;

entity detector_tb is
end detector_tb;

architecture detector_tb_beh of detector_tb is
constant T_CLOCK: time := 25 ms;
signal s1_tb: std_logic := '0';
signal s2_tb: std_logic := '0';
signal clk_cont_tb: std_logic := '0';
signal alarma_tb: std_logic;

begin

    INST_DETECTOR: entity work.detector(detector_beh)
            port map(
                    s1 => s1_tb,
                    s2 => s2_tb,
                    clk_cont => clk_cont_tb,
                    alarma => alarma_tb 
                    );
    clk_cont_tb  <= not clk_cont_tb after T_CLOCK/2;
    s1_tb <= '1' after 1000 ms, '0' after 1400 ms;
    s2_tb <= '1' after 1100 ms, '0' after 1500 ms;
end detector_tb_beh;

detector_tb.vcd
$date
  Wed Jul 12 17:42:04 2023
$end
$version
  GHDL v0
$end
$timescale
  1 fs
$end
$scope module standard $end
$upscope $end
$scope module std_logic_1164 $end
$upscope $end
$scope module numeric_std $end
$upscope $end
$scope module estados_asincronico $end
$upscope $end
$scope module detector_tb $end
$var reg 1 ! s1_tb $end
$var reg 1 " s2_tb $end
$var reg 1 # clk_cont_tb $end
$var reg 1 $ alarma_tb $end
$scope module inst_detector $end
$var reg 1 % s1 $end
$var reg 1 & s2 $end
$var reg 1 ' clk_cont $end
$var reg 1 ( alarma $end
$var reg 4 ) count[3:0] $end
$var reg 1 * rst_cont $end
$var reg 1 + delay_rst $end
$var reg 1 , comp_out $end
$var reg 1 - asinc_out $end
$var reg 1 . delay_in $end
$var reg 4 / delay_reg[3:0] $end
$scope module counter_inst $end
$var reg 1 0 ena $end
$var reg 1 1 clk $end
$var reg 1 2 rst $end
$var reg 4 3 count[3:0] $end
$var reg 4 4 aux[3:0] $end
$var integer 32 5 max $end
$upscope $end
$scope module asinc_inst $end
$var reg 1 6 s1 $end
$var reg 1 7 s2 $end
$var reg 1 8 qo $end
$comment current_state is not handled $end
$upscope $end
$upscope $end
$upscope $end
$enddefinitions $end
#0
0!
0"
0#
0$
0%
0&
0'
0(
bUUUU )
U*
U+
1,
0-
0.
b0000 /
00
01
U2
bUUUU 3
bUUUU 4
b1111 5
06
07
08
#12500000000000
1#
1'
1+
11
#25000000000000
0#
0'
01
#37500000000000
1#
1'
1*
11
12
b0000 4
#50000000000000
0#
0'
01
#62500000000000
1#
1'
b0000 )
11
b0000 3
#75000000000000
0#
0'
01
#87500000000000
1#
1'
11
#100000000000000
0#
0'
01
#112500000000000
1#
1'
11
#125000000000000
0#
0'
01
#137500000000000
1#
1'
11
#150000000000000
0#
0'
01
#162500000000000
1#
1'
11
#175000000000000
0#
0'
01
#187500000000000
1#
1'
11
#200000000000000
0#
0'
01
#212500000000000
1#
1'
11
#225000000000000
0#
0'
01
#237500000000000
1#
1'
11
#250000000000000
0#
0'
01
#262500000000000
1#
1'
11
#275000000000000
0#
0'
01
#287500000000000
1#
1'
11
#300000000000000
0#
0'
01
#312500000000000
1#
1'
11
#325000000000000
0#
0'
01
#337500000000000
1#
1'
11
#350000000000000
0#
0'
01
#362500000000000
1#
1'
11
#375000000000000
0#
0'
01
#387500000000000
1#
1'
11
#400000000000000
0#
0'
01
#412500000000000
1#
1'
11
#425000000000000
0#
0'
01
#437500000000000
1#
1'
11
#450000000000000
0#
0'
01
#462500000000000
1#
1'
11
#475000000000000
0#
0'
01
#487500000000000
1#
1'
11
#500000000000000
0#
0'
01
#512500000000000
1#
1'
11
#525000000000000
0#
0'
01
#537500000000000
1#
1'
11
#550000000000000
0#
0'
01
#562500000000000
1#
1'
11
#575000000000000
0#
0'
01
#587500000000000
1#
1'
11
#600000000000000
0#
0'
01
#612500000000000
1#
1'
11
#625000000000000
0#
0'
01
#637500000000000
1#
1'
11
#650000000000000
0#
0'
01
#662500000000000
1#
1'
11
#675000000000000
0#
0'
01
#687500000000000
1#
1'
11
#700000000000000
0#
0'
01
#712500000000000
1#
1'
11
#725000000000000
0#
0'
01
#737500000000000
1#
1'
11
#750000000000000
0#
0'
01
#762500000000000
1#
1'
11
#775000000000000
0#
0'
01
#787500000000000
1#
1'
11
#800000000000000
0#
0'
01
#812500000000000
1#
1'
11
#825000000000000
0#
0'
01
#837500000000000
1#
1'
11
#850000000000000
0#
0'
01
#862500000000000
1#
1'
11
#875000000000000
0#
0'
01
#887500000000000
1#
1'
11
#900000000000000
0#
0'
01
#912500000000000
1#
1'
11
#925000000000000
0#
0'
01
#937500000000000
1#
1'
11
#950000000000000
0#
0'
01
#962500000000000
1#
1'
11
#975000000000000
0#
0'
01
#987500000000000
1#
1'
11
#1000000000000000
1!
0#
1%
0'
1-
10
01
16
18
#1012500000000000
1#
1'
0*
11
02
b0001 4
#1025000000000000
0#
0'
0,
01
#1037500000000000
1#
1'
b0001 )
11
b0001 3
b0010 4
#1050000000000000
0#
0'
01
#1062500000000000
1#
1'
b0010 )
11
b0010 3
b0011 4
#1075000000000000
0#
0'
01
#1087500000000000
1#
1'
b0011 )
11
b0011 3
b0100 4
#1100000000000000
1"
0#
1&
0'
0-
1.
00
01
17
08
#1112500000000000
1#
1$
1'
1(
b0100 )
1*
b0001 /
11
12
b0100 3
b0000 4
#1125000000000000
0#
0'
1,
01
#1137500000000000
1#
1'
b0000 )
0.
b0011 /
11
b0000 3
#1150000000000000
0#
0'
01
#1162500000000000
1#
1'
b0110 /
11
#1175000000000000
0#
0'
01
#1187500000000000
1#
1'
b1100 /
11
#1200000000000000
0#
0'
01
#1212500000000000
1#
1'
b1000 /
11
#1225000000000000
0#
0'
01
#1237500000000000
1#
0$
1'
0(
b0000 /
11
#1250000000000000
0#
0'
01
#1262500000000000
1#
1'
11
#1275000000000000
0#
0'
01
#1287500000000000
1#
1'
11
#1300000000000000
0#
0'
01
#1312500000000000
1#
1'
11
#1325000000000000
0#
0'
01
#1337500000000000
1#
1'
11
#1350000000000000
0#
0'
01
#1362500000000000
1#
1'
11
#1375000000000000
0#
0'
01
#1387500000000000
1#
1'
11
#1400000000000000
0!
0#
0%
0'
01
06
#1412500000000000
1#
1'
11
#1425000000000000
0#
0'
01
#1437500000000000
1#
1'
11
#1450000000000000
0#
0'
01
#1462500000000000
1#
1'
11
#1475000000000000
0#
0'
01
#1487500000000000
1#
1'
11
#1500000000000000
0"
0#
0&
0'
01
07
